setup.cfg
setup.py
olaf/__init__.py
olaf/cli.py
olaf.egg-info/PKG-INFO
olaf.egg-info/SOURCES.txt
olaf.egg-info/dependency_links.txt
olaf.egg-info/entry_points.txt
olaf.egg-info/not-zip-safe
olaf.egg-info/requires.txt
olaf.egg-info/top_level.txt