Metadata-Version: 1.1
Name: olaf
Version: 0.1.4
Summary: Helps to manage multiple requirements files.
Home-page: https://github.com/hactar-is/olaf
Author: Andy Beaumont
Author-email: andy@hactar.is
License: MIT
Platform: any
Classifier: Development Status :: 4 - Beta
Classifier: Environment :: Console
Classifier: Intended Audience :: Developers
Classifier: License :: OSI Approved :: MIT License
Classifier: Operating System :: POSIX
Classifier: Operating System :: MacOS
Classifier: Operating System :: Unix
Classifier: Programming Language :: Python
Classifier: Programming Language :: Python :: 2
Classifier: Programming Language :: Python :: 3
Classifier: Topic :: Software Development :: Libraries :: Python Modules
